CHANGES.rst
MANIFEST.in
README.md
README.rst
setup.py
kokolog/__init__.py
kokolog/aboutfile.py
kokolog/character.py
kokolog/prettyprint.py
kokolog.egg-info/PKG-INFO
kokolog.egg-info/SOURCES.txt
kokolog.egg-info/dependency_links.txt
kokolog.egg-info/top_level.txt