Metadata-Version: 1.0
Name: kokolog
Version: 0.0.1
Summary: wecatch kokolog
Home-page: https://github.com/listen-lavender/kokolog
Author: haokuan
Author-email: jingdaohao@gmail.com
License: UNKNOWN
Keywords: wecatch >
Platform: UNKNOWN
